{
    "version": "4.1.280",
    "description": "The ElasticMapReduce module of AWS Tools for PowerShell lets developers and administrators manage Amazon Elastic MapReduce from the PowerShell scripting environment",
    "homepage": "https://github.com/aws/aws-tools-for-powershell",
    "license": "Apache-2.0",
    "url": "https://psg-prod-eastus.azureedge.net/packages/aws.tools.elasticmapreduce.4.1.280.nupkg",
    "hash": "e0fa04e646505b03099e956aaec7dd8e4b7f30ecf29aa0289105e0ba76ed39d7",
    "depends": "aws-tools-powershell-common",
    "psmodule": {
        "name": "AWS.Tools.ElasticMapReduce"
    },
    "checkver": {
        "url": "https://www.powershellgallery.com/packages/AWS.Tools.ElasticMapReduce",
        "regex": "Downloads? of ([\\d.]+)"
    },
    "autoupdate": {
        "url": "https://psg-prod-eastus.azureedge.net/packages/aws.tools.elasticmapreduce.$version.nupkg"
    }
}
