{
    "version": "4.1.366",
    "description": "The Panorama module of AWS Tools for PowerShell lets developers and administrators manage AWS Panorama from the PowerShell scripting environment",
    "homepage": "https://github.com/aws/aws-tools-for-powershell",
    "license": "Apache-2.0",
    "url": "https://psg-prod-eastus.azureedge.net/packages/aws.tools.panorama.4.1.366.nupkg",
    "hash": "af3ec2a07af23f63e5f3bea8c19d2bedd46c8c5b7c93b4a45a7e34d51ca79efe",
    "depends": "aws-tools-powershell-common",
    "psmodule": {
        "name": "AWS.Tools.Panorama"
    },
    "checkver": {
        "url": "https://www.powershellgallery.com/packages/AWS.Tools.Panorama",
        "regex": "Downloads? of ([\\d.]+)"
    },
    "autoupdate": {
        "url": "https://psg-prod-eastus.azureedge.net/packages/aws.tools.panorama.$version.nupkg"
    }
}
