{
    "version": "4.1.312",
    "description": "The HealthLake module of AWS Tools for PowerShell lets developers and administrators manage Amazon HealthLake from the PowerShell scripting environment",
    "homepage": "https://github.com/aws/aws-tools-for-powershell",
    "license": "Apache-2.0",
    "url": "https://psg-prod-eastus.azureedge.net/packages/aws.tools.healthlake.4.1.312.nupkg",
    "hash": "c49f8cf484f458af0442dbd3c2fe7498ae327ec2c5dd5a09ca85e51bdedd1877",
    "depends": "aws-tools-powershell-common",
    "psmodule": {
        "name": "AWS.Tools.HealthLake"
    },
    "checkver": {
        "url": "https://www.powershellgallery.com/packages/AWS.Tools.HealthLake",
        "regex": "Downloads? of ([\\d.]+)"
    },
    "autoupdate": {
        "url": "https://psg-prod-eastus.azureedge.net/packages/aws.tools.healthlake.$version.nupkg"
    }
}
