{
    "version": "4.1.540",
    "description": "The ResourceGroupsTaggingAPI module of AWS Tools for PowerShell lets developers and administrators manage AWS Resource Groups Tagging API from the PowerShell scripting environment",
    "homepage": "https://github.com/aws/aws-tools-for-powershell",
    "license": "Apache-2.0",
    "url": "https://psg-prod-eastus.azureedge.net/packages/aws.tools.resourcegroupstaggingapi.4.1.540.nupkg",
    "hash": "636e3a6a6b3a58ffba19e016ad2b3f5079b24b357da549746836da902711982e",
    "depends": "aws-tools-powershell-common",
    "psmodule": {
        "name": "AWS.Tools.ResourceGroupsTaggingAPI"
    },
    "checkver": {
        "url": "https://www.powershellgallery.com/packages/AWS.Tools.ResourceGroupsTaggingAPI",
        "regex": "Downloads? of ([\\d.]+)"
    },
    "autoupdate": {
        "url": "https://psg-prod-eastus.azureedge.net/packages/aws.tools.resourcegroupstaggingapi.$version.nupkg"
    }
}
