{
    "version": "4.1.274",
    "description": "The AWSHealth module of AWS Tools for PowerShell lets developers and administrators manage AWS Health from the PowerShell scripting environment",
    "homepage": "https://github.com/aws/aws-tools-for-powershell",
    "license": "Apache-2.0",
    "url": "https://psg-prod-eastus.azureedge.net/packages/aws.tools.awshealth.4.1.274.nupkg",
    "hash": "d120af11d2b0ded78b6509174883a4c2e380e916730997abb3784e558eb17c7b",
    "depends": "aws-tools-powershell-common",
    "psmodule": {
        "name": "AWS.Tools.AWSHealth"
    },
    "checkver": {
        "url": "https://www.powershellgallery.com/packages/AWS.Tools.AWSHealth",
        "regex": "Downloads? of ([\\d.]+)"
    },
    "autoupdate": {
        "url": "https://psg-prod-eastus.azureedge.net/packages/aws.tools.awshealth.$version.nupkg"
    }
}
