{
    "version": "4.1.424",
    "description": "The CodeCommit module of AWS Tools for PowerShell lets developers and administrators manage AWS CodeCommit from the PowerShell scripting environment",
    "homepage": "https://github.com/aws/aws-tools-for-powershell",
    "license": "Apache-2.0",
    "url": "https://psg-prod-eastus.azureedge.net/packages/aws.tools.codecommit.4.1.424.nupkg",
    "hash": "1e655d2e0272637efc5ee40bbfd229b5946f900108df736e5d75fd909fef2cee",
    "depends": "aws-tools-powershell-common",
    "psmodule": {
        "name": "AWS.Tools.CodeCommit"
    },
    "checkver": {
        "url": "https://www.powershellgallery.com/packages/AWS.Tools.CodeCommit",
        "regex": "Downloads? of ([\\d.]+)"
    },
    "autoupdate": {
        "url": "https://psg-prod-eastus.azureedge.net/packages/aws.tools.codecommit.$version.nupkg"
    }
}
