{
    "version": "4.1.379",
    "description": "The CloudSearchDomain module of AWS Tools for PowerShell lets developers and administrators manage Amazon CloudSearch Domain from the PowerShell scripting environment",
    "homepage": "https://github.com/aws/aws-tools-for-powershell",
    "license": "Apache-2.0",
    "url": "https://psg-prod-eastus.azureedge.net/packages/aws.tools.cloudsearchdomain.4.1.379.nupkg",
    "hash": "000c956edf4d272551ba4a6e602bbdc93a05ae7188c574ce843f40211df464f4",
    "depends": "aws-tools-powershell-common",
    "psmodule": {
        "name": "AWS.Tools.CloudSearchDomain"
    },
    "checkver": {
        "url": "https://www.powershellgallery.com/packages/AWS.Tools.CloudSearchDomain",
        "regex": "Downloads? of ([\\d.]+)"
    },
    "autoupdate": {
        "url": "https://psg-prod-eastus.azureedge.net/packages/aws.tools.cloudsearchdomain.$version.nupkg"
    }
}
