{
    "version": "4.1.443",
    "description": "The WellArchitected module of AWS Tools for PowerShell lets developers and administrators manage AWS Well-Architected Tool from the PowerShell scripting environment",
    "homepage": "https://github.com/aws/aws-tools-for-powershell",
    "license": "Apache-2.0",
    "url": "https://psg-prod-eastus.azureedge.net/packages/aws.tools.wellarchitected.4.1.443.nupkg",
    "hash": "495b39ad070056e4bb752fa70a97d989ddaab089a685a52822b9ea9156c66984",
    "depends": "aws-tools-powershell-common",
    "psmodule": {
        "name": "AWS.Tools.WellArchitected"
    },
    "checkver": {
        "url": "https://www.powershellgallery.com/packages/AWS.Tools.WellArchitected",
        "regex": "Downloads? of ([\\d.]+)"
    },
    "autoupdate": {
        "url": "https://psg-prod-eastus.azureedge.net/packages/aws.tools.wellarchitected.$version.nupkg"
    }
}
