{
    "version": "4.1.618",
    "description": "The Pinpoint module of AWS Tools for PowerShell lets developers and administrators manage Amazon Pinpoint from the PowerShell scripting environment",
    "homepage": "https://github.com/aws/aws-tools-for-powershell",
    "license": "Apache-2.0",
    "url": "https://psg-prod-eastus.azureedge.net/packages/aws.tools.pinpoint.4.1.618.nupkg",
    "hash": "ceaf108ece9f9583888f68cd8e02aea34d8c45300baa022d0a84e5c02e567287",
    "depends": "aws-tools-powershell-common",
    "psmodule": {
        "name": "AWS.Tools.Pinpoint"
    },
    "checkver": {
        "url": "https://www.powershellgallery.com/packages/AWS.Tools.Pinpoint",
        "regex": "Downloads? of ([\\d.]+)"
    },
    "autoupdate": {
        "url": "https://psg-prod-eastus.azureedge.net/packages/aws.tools.pinpoint.$version.nupkg"
    }
}
