{
    "version": "4.1.485",
    "description": "The SecurityHub module of AWS Tools for PowerShell lets developers and administrators manage AWS Security Hub from the PowerShell scripting environment",
    "homepage": "https://github.com/aws/aws-tools-for-powershell",
    "license": "Apache-2.0",
    "url": "https://psg-prod-eastus.azureedge.net/packages/aws.tools.securityhub.4.1.485.nupkg",
    "hash": "0dfbe6676e9a4c5ce2dcc1e3040ec7437b019dda03196b7e6edfeb09c092fb55",
    "depends": "aws-tools-powershell-common",
    "psmodule": {
        "name": "AWS.Tools.SecurityHub"
    },
    "checkver": {
        "url": "https://www.powershellgallery.com/packages/AWS.Tools.SecurityHub",
        "regex": "Downloads? of ([\\d.]+)"
    },
    "autoupdate": {
        "url": "https://psg-prod-eastus.azureedge.net/packages/aws.tools.securityhub.$version.nupkg"
    }
}
