{
    "version": "4.1.525",
    "description": "The QLDB module of AWS Tools for PowerShell lets developers and administrators manage Amazon QLDB from the PowerShell scripting environment",
    "homepage": "https://github.com/aws/aws-tools-for-powershell",
    "license": "Apache-2.0",
    "url": "https://psg-prod-eastus.azureedge.net/packages/aws.tools.qldb.4.1.525.nupkg",
    "hash": "50a763f57c1d94ccbbaab13cb09fe950f6ecc3455ad8306717a1e8ab24f744ca",
    "depends": "aws-tools-powershell-common",
    "psmodule": {
        "name": "AWS.Tools.QLDB"
    },
    "checkver": {
        "url": "https://www.powershellgallery.com/packages/AWS.Tools.QLDB",
        "regex": "Downloads? of ([\\d.]+)"
    },
    "autoupdate": {
        "url": "https://psg-prod-eastus.azureedge.net/packages/aws.tools.qldb.$version.nupkg"
    }
}
