{
    "version": "4.1.350",
    "description": "The StorageGateway module of AWS Tools for PowerShell lets developers and administrators manage AWS Storage Gateway from the PowerShell scripting environment",
    "homepage": "https://github.com/aws/aws-tools-for-powershell",
    "license": "Apache-2.0",
    "url": "https://psg-prod-eastus.azureedge.net/packages/aws.tools.storagegateway.4.1.350.nupkg",
    "hash": "f76ac0fd0b723e7d4c8927ae596198f10e2409bf3c162778cadf7ed44f310f72",
    "depends": "aws-tools-powershell-common",
    "psmodule": {
        "name": "AWS.Tools.StorageGateway"
    },
    "checkver": {
        "url": "https://www.powershellgallery.com/packages/AWS.Tools.StorageGateway",
        "regex": "Downloads? of ([\\d.]+)"
    },
    "autoupdate": {
        "url": "https://psg-prod-eastus.azureedge.net/packages/aws.tools.storagegateway.$version.nupkg"
    }
}
