{
    "version": "4.1.582",
    "description": "The Lex module of AWS Tools for PowerShell lets developers and administrators manage Amazon Lex from the PowerShell scripting environment",
    "homepage": "https://github.com/aws/aws-tools-for-powershell",
    "license": "Apache-2.0",
    "url": "https://psg-prod-eastus.azureedge.net/packages/aws.tools.lex.4.1.582.nupkg",
    "hash": "1600d951d9d128a75c79bcf9fa9831038480827192b9cc8921f16237b089c63f",
    "depends": "aws-tools-powershell-common",
    "psmodule": {
        "name": "AWS.Tools.Lex"
    },
    "checkver": {
        "url": "https://www.powershellgallery.com/packages/AWS.Tools.Lex",
        "regex": "Downloads? of ([\\d.]+)"
    },
    "autoupdate": {
        "url": "https://psg-prod-eastus.azureedge.net/packages/aws.tools.lex.$version.nupkg"
    }
}
