{
    "version": "4.1.577",
    "description": "The Elasticsearch module of AWS Tools for PowerShell lets developers and administrators manage Amazon Elasticsearch from the PowerShell scripting environment",
    "homepage": "https://github.com/aws/aws-tools-for-powershell",
    "license": "Apache-2.0",
    "url": "https://psg-prod-eastus.azureedge.net/packages/aws.tools.elasticsearch.4.1.577.nupkg",
    "hash": "627804d5d1a68fe32ff2bba69aa1b25a7af8cbac4fce35787d9f5b628c4bff75",
    "depends": "aws-tools-powershell-common",
    "psmodule": {
        "name": "AWS.Tools.Elasticsearch"
    },
    "checkver": {
        "url": "https://www.powershellgallery.com/packages/AWS.Tools.Elasticsearch",
        "regex": "Downloads? of ([\\d.]+)"
    },
    "autoupdate": {
        "url": "https://psg-prod-eastus.azureedge.net/packages/aws.tools.elasticsearch.$version.nupkg"
    }
}
