{
    "version": "4.1.264",
    "description": "The CloudSearchDomain module of AWS Tools for PowerShell lets developers and administrators manage Amazon CloudSearch Domain from the PowerShell scripting environment",
    "homepage": "https://github.com/aws/aws-tools-for-powershell",
    "license": "Apache-2.0",
    "url": "https://psg-prod-eastus.azureedge.net/packages/aws.tools.cloudsearchdomain.4.1.264.nupkg",
    "hash": "b0eacdf0e93bc1c2c84c587209b431e170b3e7ffc0e0791fd21bff9261232b7e",
    "depends": "aws-tools-powershell-common",
    "psmodule": {
        "name": "AWS.Tools.CloudSearchDomain"
    },
    "checkver": {
        "url": "https://www.powershellgallery.com/packages/AWS.Tools.CloudSearchDomain",
        "regex": "Downloads? of ([\\d.]+)"
    },
    "autoupdate": {
        "url": "https://psg-prod-eastus.azureedge.net/packages/aws.tools.cloudsearchdomain.$version.nupkg"
    }
}
