{
    "version": "4.1.468",
    "description": "The Organizations module of AWS Tools for PowerShell lets developers and administrators manage AWS Organizations from the PowerShell scripting environment",
    "homepage": "https://github.com/aws/aws-tools-for-powershell",
    "license": "Apache-2.0",
    "url": "https://psg-prod-eastus.azureedge.net/packages/aws.tools.organizations.4.1.468.nupkg",
    "hash": "333c95ce423df6ec73cfaa024e17258461d3c061506150b888fa3165079fe865",
    "depends": "aws-tools-powershell-common",
    "psmodule": {
        "name": "AWS.Tools.Organizations"
    },
    "checkver": {
        "url": "https://www.powershellgallery.com/packages/AWS.Tools.Organizations",
        "regex": "Downloads? of ([\\d.]+)"
    },
    "autoupdate": {
        "url": "https://psg-prod-eastus.azureedge.net/packages/aws.tools.organizations.$version.nupkg"
    }
}
