{
    "version": "4.1.471",
    "description": "The LookoutEquipment module of AWS Tools for PowerShell lets developers and administrators manage Amazon Lookout for Equipment from the PowerShell scripting environment",
    "homepage": "https://github.com/aws/aws-tools-for-powershell",
    "license": "Apache-2.0",
    "url": "https://psg-prod-eastus.azureedge.net/packages/aws.tools.lookoutequipment.4.1.471.nupkg",
    "hash": "36f21b469cb3eaf367611a38a8d1004b1ab4f65d4d403d2cd706f1f6841c6133",
    "depends": "aws-tools-powershell-common",
    "psmodule": {
        "name": "AWS.Tools.LookoutEquipment"
    },
    "checkver": {
        "url": "https://www.powershellgallery.com/packages/AWS.Tools.LookoutEquipment",
        "regex": "Downloads? of ([\\d.]+)"
    },
    "autoupdate": {
        "url": "https://psg-prod-eastus.azureedge.net/packages/aws.tools.lookoutequipment.$version.nupkg"
    }
}
