{
    "version": "4.1.413",
    "description": "The APIGateway module of AWS Tools for PowerShell lets developers and administrators manage Amazon API Gateway from the PowerShell scripting environment",
    "homepage": "https://github.com/aws/aws-tools-for-powershell",
    "license": "Apache-2.0",
    "url": "https://psg-prod-eastus.azureedge.net/packages/aws.tools.apigateway.4.1.413.nupkg",
    "hash": "35486c32e2ddb106e70b590588d1dc8051473adf3f3ba4c1cb1012d181ec8a0f",
    "depends": "aws-tools-powershell-common",
    "psmodule": {
        "name": "AWS.Tools.APIGateway"
    },
    "checkver": {
        "url": "https://www.powershellgallery.com/packages/AWS.Tools.APIGateway",
        "regex": "Downloads? of ([\\d.]+)"
    },
    "autoupdate": {
        "url": "https://psg-prod-eastus.azureedge.net/packages/aws.tools.apigateway.$version.nupkg"
    }
}
