{
    "version": "4.1.681",
    "description": "The ElasticBeanstalk module of AWS Tools for PowerShell lets developers and administrators manage AWS Elastic Beanstalk from the PowerShell scripting environment",
    "homepage": "https://github.com/aws/aws-tools-for-powershell",
    "license": "Apache-2.0",
    "url": "https://psg-prod-eastus.azureedge.net/packages/aws.tools.elasticbeanstalk.4.1.681.nupkg",
    "hash": "7faa44bfeb63724927d4c819c8dbe5a73664906cd3aeab1ad55ab3c64a4664e5",
    "depends": "aws-tools-powershell-common",
    "psmodule": {
        "name": "AWS.Tools.ElasticBeanstalk"
    },
    "checkver": {
        "url": "https://www.powershellgallery.com/packages/AWS.Tools.ElasticBeanstalk",
        "regex": "Downloads? of ([\\d.]+)"
    },
    "autoupdate": {
        "url": "https://psg-prod-eastus.azureedge.net/packages/aws.tools.elasticbeanstalk.$version.nupkg"
    }
}
