{
    "version": "4.1.533",
    "description": "The ECRPublic module of AWS Tools for PowerShell lets developers and administrators manage Amazon Elastic Container Registry Public from the PowerShell scripting environment",
    "homepage": "https://github.com/aws/aws-tools-for-powershell",
    "license": "Apache-2.0",
    "url": "https://psg-prod-eastus.azureedge.net/packages/aws.tools.ecrpublic.4.1.533.nupkg",
    "hash": "ddb60db4175f9b4197446f9469bc146a0f19fd38b12b10411deca778e8c56c24",
    "depends": "aws-tools-powershell-common",
    "psmodule": {
        "name": "AWS.Tools.ECRPublic"
    },
    "checkver": {
        "url": "https://www.powershellgallery.com/packages/AWS.Tools.ECRPublic",
        "regex": "Downloads? of ([\\d.]+)"
    },
    "autoupdate": {
        "url": "https://psg-prod-eastus.azureedge.net/packages/aws.tools.ecrpublic.$version.nupkg"
    }
}
