{
    "version": "4.1.457",
    "description": "The SimpleEmail module of AWS Tools for PowerShell lets developers and administrators manage Amazon Simple Email Service (SES) from the PowerShell scripting environment",
    "homepage": "https://github.com/aws/aws-tools-for-powershell",
    "license": "Apache-2.0",
    "url": "https://psg-prod-eastus.azureedge.net/packages/aws.tools.simpleemail.4.1.457.nupkg",
    "hash": "12244d81be4aa4bdd6e872c374cd4be7f26ea7234559eb0fc14d286496a0b18a",
    "depends": "aws-tools-powershell-common",
    "psmodule": {
        "name": "AWS.Tools.SimpleEmail"
    },
    "checkver": {
        "url": "https://www.powershellgallery.com/packages/AWS.Tools.SimpleEmail",
        "regex": "Downloads? of ([\\d.]+)"
    },
    "autoupdate": {
        "url": "https://psg-prod-eastus.azureedge.net/packages/aws.tools.simpleemail.$version.nupkg"
    }
}
