{
    "version": "4.1.496",
    "description": "The LakeFormation module of AWS Tools for PowerShell lets developers and administrators manage AWS Lake Formation from the PowerShell scripting environment",
    "homepage": "https://github.com/aws/aws-tools-for-powershell",
    "license": "Apache-2.0",
    "url": "https://psg-prod-eastus.azureedge.net/packages/aws.tools.lakeformation.4.1.496.nupkg",
    "hash": "eb1b24d7a2b589b96aa277bbf7ddb42c38e81af113c91b96aa34fcaca2d4b2c5",
    "depends": "aws-tools-powershell-common",
    "psmodule": {
        "name": "AWS.Tools.LakeFormation"
    },
    "checkver": {
        "url": "https://www.powershellgallery.com/packages/AWS.Tools.LakeFormation",
        "regex": "Downloads? of ([\\d.]+)"
    },
    "autoupdate": {
        "url": "https://psg-prod-eastus.azureedge.net/packages/aws.tools.lakeformation.$version.nupkg"
    }
}
