{
    "version": "4.1.594",
    "description": "The ApplicationAutoScaling module of AWS Tools for PowerShell lets developers and administrators manage Application Auto Scaling from the PowerShell scripting environment",
    "homepage": "https://github.com/aws/aws-tools-for-powershell",
    "license": "Apache-2.0",
    "url": "https://psg-prod-eastus.azureedge.net/packages/aws.tools.applicationautoscaling.4.1.594.nupkg",
    "hash": "821b516458a53e75b6eaadb832fb2d3f5dfb38cd917e8fa217f38c5127f9e721",
    "depends": "aws-tools-powershell-common",
    "psmodule": {
        "name": "AWS.Tools.ApplicationAutoScaling"
    },
    "checkver": {
        "url": "https://www.powershellgallery.com/packages/AWS.Tools.ApplicationAutoScaling",
        "regex": "Downloads? of ([\\d.]+)"
    },
    "autoupdate": {
        "url": "https://psg-prod-eastus.azureedge.net/packages/aws.tools.applicationautoscaling.$version.nupkg"
    }
}
