{
    "version": "4.1.260",
    "description": "The AWSSupport module of AWS Tools for PowerShell lets developers and administrators manage AWS Support from the PowerShell scripting environment",
    "homepage": "https://github.com/aws/aws-tools-for-powershell",
    "license": "Apache-2.0",
    "url": "https://psg-prod-eastus.azureedge.net/packages/aws.tools.awssupport.4.1.260.nupkg",
    "hash": "304e523dcba855828a5fcdf880205b48e0f7d3661f8c70dd3e6920dadf03ccbc",
    "depends": "aws-tools-powershell-common",
    "psmodule": {
        "name": "AWS.Tools.AWSSupport"
    },
    "checkver": {
        "url": "https://www.powershellgallery.com/packages/AWS.Tools.AWSSupport",
        "regex": "Downloads? of ([\\d.]+)"
    },
    "autoupdate": {
        "url": "https://psg-prod-eastus.azureedge.net/packages/aws.tools.awssupport.$version.nupkg"
    }
}
