{
    "version": "4.1.181",
    "description": "The AWSMarketplaceCommerceAnalytics module of AWS Tools for PowerShell lets developers and administrators manage AWS Marketplace Commerce Analytics from the PowerShell scripting environment",
    "homepage": "https://github.com/aws/aws-tools-for-powershell",
    "license": "Apache-2.0",
    "url": "https://psg-prod-eastus.azureedge.net/packages/aws.tools.awsmarketplacecommerceanalytics.4.1.181.nupkg",
    "hash": "9268521b23eaeb785a64e26109b7f16efb283e386054ce2854e33a001554b58c",
    "depends": "aws-tools-powershell-common",
    "psmodule": {
        "name": "AWS.Tools.AWSMarketplaceCommerceAnalytics"
    },
    "checkver": {
        "url": "https://www.powershellgallery.com/packages/AWS.Tools.AWSMarketplaceCommerceAnalytics",
        "regex": "Downloads? of ([\\d.]+)"
    },
    "autoupdate": {
        "url": "https://psg-prod-eastus.azureedge.net/packages/aws.tools.awsmarketplacecommerceanalytics.$version.nupkg"
    }
}
