{
    "version": "4.1.164",
    "description": "The FIS module of AWS Tools for PowerShell lets developers and administrators manage AWS Fault Injection Simulator from the PowerShell scripting environment",
    "homepage": "https://github.com/aws/aws-tools-for-powershell",
    "license": "Apache-2.0",
    "url": "https://psg-prod-eastus.azureedge.net/packages/aws.tools.fis.4.1.164.nupkg",
    "hash": "8eb375920bf5c40bec6d8bdb46821cf23a2fcaa3dc50fff1e892ab9738f4118b",
    "depends": "aws-tools-powershell-common",
    "psmodule": {
        "name": "AWS.Tools.FIS"
    },
    "checkver": {
        "url": "https://www.powershellgallery.com/packages/AWS.Tools.FIS",
        "regex": "Downloads? of ([\\d.]+)"
    },
    "autoupdate": {
        "url": "https://psg-prod-eastus.azureedge.net/packages/aws.tools.fis.$version.nupkg"
    }
}
