{
    "version": "4.1.291",
    "description": "The ElasticLoadBalancing module of AWS Tools for PowerShell lets developers and administrators manage Elastic Load Balancing from the PowerShell scripting environment",
    "homepage": "https://github.com/aws/aws-tools-for-powershell",
    "license": "Apache-2.0",
    "url": "https://psg-prod-eastus.azureedge.net/packages/aws.tools.elasticloadbalancing.4.1.291.nupkg",
    "hash": "44e1ef14ca084f7ceb3719fa15aecdcd515260535c87887871b89eb0d3ef202d",
    "depends": "aws-tools-powershell-common",
    "psmodule": {
        "name": "AWS.Tools.ElasticLoadBalancing"
    },
    "checkver": {
        "url": "https://www.powershellgallery.com/packages/AWS.Tools.ElasticLoadBalancing",
        "regex": "Downloads? of ([\\d.]+)"
    },
    "autoupdate": {
        "url": "https://psg-prod-eastus.azureedge.net/packages/aws.tools.elasticloadbalancing.$version.nupkg"
    }
}
