{
    "version": "4.1.553",
    "description": "The CloudWatchRUM module of AWS Tools for PowerShell lets developers and administrators manage CloudWatch RUM from the PowerShell scripting environment",
    "homepage": "https://github.com/aws/aws-tools-for-powershell",
    "license": "Apache-2.0",
    "url": "https://psg-prod-eastus.azureedge.net/packages/aws.tools.cloudwatchrum.4.1.553.nupkg",
    "hash": "38e34423d4f6467efeb6a269aff85d278e3b462f203ea5a23c6e86a97b03afe6",
    "depends": "aws-tools-powershell-common",
    "psmodule": {
        "name": "AWS.Tools.CloudWatchRUM"
    },
    "checkver": {
        "url": "https://www.powershellgallery.com/packages/AWS.Tools.CloudWatchRUM",
        "regex": "Downloads? of ([\\d.]+)"
    },
    "autoupdate": {
        "url": "https://psg-prod-eastus.azureedge.net/packages/aws.tools.cloudwatchrum.$version.nupkg"
    }
}
