{
    "version": "4.1.182",
    "description": "The FinSpaceData module of AWS Tools for PowerShell lets developers and administrators manage FinSpace Public API from the PowerShell scripting environment",
    "homepage": "https://github.com/aws/aws-tools-for-powershell",
    "license": "Apache-2.0",
    "url": "https://psg-prod-eastus.azureedge.net/packages/aws.tools.finspacedata.4.1.182.nupkg",
    "hash": "7d11e3e382fc4d5f6f0f9b15ebfc7fe881480885b414f719a8a6a163eaa984ed",
    "depends": "aws-tools-powershell-common",
    "psmodule": {
        "name": "AWS.Tools.FinSpaceData"
    },
    "checkver": {
        "url": "https://www.powershellgallery.com/packages/AWS.Tools.FinSpaceData",
        "regex": "Downloads? of ([\\d.]+)"
    },
    "autoupdate": {
        "url": "https://psg-prod-eastus.azureedge.net/packages/aws.tools.finspacedata.$version.nupkg"
    }
}
