{
    "version": "4.1.552",
    "description": "The EKS module of AWS Tools for PowerShell lets developers and administrators manage Amazon Elastic Container Service for Kubernetes from the PowerShell scripting environment",
    "homepage": "https://github.com/aws/aws-tools-for-powershell",
    "license": "Apache-2.0",
    "url": "https://psg-prod-eastus.azureedge.net/packages/aws.tools.eks.4.1.552.nupkg",
    "hash": "b0dbf9fdb348377482a27710b219d5818386e68035dcdb04a3f42ddaf66ee65a",
    "depends": "aws-tools-powershell-common",
    "psmodule": {
        "name": "AWS.Tools.EKS"
    },
    "checkver": {
        "url": "https://www.powershellgallery.com/packages/AWS.Tools.EKS",
        "regex": "Downloads? of ([\\d.]+)"
    },
    "autoupdate": {
        "url": "https://psg-prod-eastus.azureedge.net/packages/aws.tools.eks.$version.nupkg"
    }
}
