{
    "version": "4.1.404",
    "description": "The Greengrass module of AWS Tools for PowerShell lets developers and administrators manage AWS Greengrass from the PowerShell scripting environment",
    "homepage": "https://github.com/aws/aws-tools-for-powershell",
    "license": "Apache-2.0",
    "url": "https://psg-prod-eastus.azureedge.net/packages/aws.tools.greengrass.4.1.404.nupkg",
    "hash": "330d8a6cdbc5c78bebd9f608e393ec4c9a67c6e6c3a207c5f5a69c254eaf0cc2",
    "depends": "aws-tools-powershell-common",
    "psmodule": {
        "name": "AWS.Tools.Greengrass"
    },
    "checkver": {
        "url": "https://www.powershellgallery.com/packages/AWS.Tools.Greengrass",
        "regex": "Downloads? of ([\\d.]+)"
    },
    "autoupdate": {
        "url": "https://psg-prod-eastus.azureedge.net/packages/aws.tools.greengrass.$version.nupkg"
    }
}
