{
    "version": "4.1.274",
    "description": "The ServerlessApplicationRepository module of AWS Tools for PowerShell lets developers and administrators manage AWS Serverless Application Repository from the PowerShell scripting environment",
    "homepage": "https://github.com/aws/aws-tools-for-powershell",
    "license": "Apache-2.0",
    "url": "https://psg-prod-eastus.azureedge.net/packages/aws.tools.serverlessapplicationrepository.4.1.274.nupkg",
    "hash": "5b6a8126296d5602a2008755dd5a89dfbff3e902cdc860e208dab52c7078e588",
    "depends": "aws-tools-powershell-common",
    "psmodule": {
        "name": "AWS.Tools.ServerlessApplicationRepository"
    },
    "checkver": {
        "url": "https://www.powershellgallery.com/packages/AWS.Tools.ServerlessApplicationRepository",
        "regex": "Downloads? of ([\\d.]+)"
    },
    "autoupdate": {
        "url": "https://psg-prod-eastus.azureedge.net/packages/aws.tools.serverlessapplicationrepository.$version.nupkg"
    }
}
