{
    "version": "4.1.294",
    "description": "The ConfigService module of AWS Tools for PowerShell lets developers and administrators manage AWS Config from the PowerShell scripting environment",
    "homepage": "https://github.com/aws/aws-tools-for-powershell",
    "license": "Apache-2.0",
    "url": "https://psg-prod-eastus.azureedge.net/packages/aws.tools.configservice.4.1.294.nupkg",
    "hash": "054f528c832d50c3b732b2e95798c5d139736e501d16c60fb7191cf71aa7c568",
    "depends": "aws-tools-powershell-common",
    "psmodule": {
        "name": "AWS.Tools.ConfigService"
    },
    "checkver": {
        "url": "https://www.powershellgallery.com/packages/AWS.Tools.ConfigService",
        "regex": "Downloads? of ([\\d.]+)"
    },
    "autoupdate": {
        "url": "https://psg-prod-eastus.azureedge.net/packages/aws.tools.configservice.$version.nupkg"
    }
}
