{
    "version": "4.1.567",
    "description": "The AmplifyBackend module of AWS Tools for PowerShell lets developers and administrators manage Amplify Backend from the PowerShell scripting environment",
    "homepage": "https://github.com/aws/aws-tools-for-powershell",
    "license": "Apache-2.0",
    "url": "https://psg-prod-eastus.azureedge.net/packages/aws.tools.amplifybackend.4.1.567.nupkg",
    "hash": "17c9a122ff391faebc14663fdf281f90d3f821257350394b72675e59fb0e06f8",
    "depends": "aws-tools-powershell-common",
    "psmodule": {
        "name": "AWS.Tools.AmplifyBackend"
    },
    "checkver": {
        "url": "https://www.powershellgallery.com/packages/AWS.Tools.AmplifyBackend",
        "regex": "Downloads? of ([\\d.]+)"
    },
    "autoupdate": {
        "url": "https://psg-prod-eastus.azureedge.net/packages/aws.tools.amplifybackend.$version.nupkg"
    }
}
