{
    "version": "4.1.173",
    "description": "The ApiGatewayManagementApi module of AWS Tools for PowerShell lets developers and administrators manage Amazon API Gateway Management API from the PowerShell scripting environment",
    "homepage": "https://github.com/aws/aws-tools-for-powershell",
    "license": "Apache-2.0",
    "url": "https://psg-prod-eastus.azureedge.net/packages/aws.tools.apigatewaymanagementapi.4.1.173.nupkg",
    "hash": "f3513c6efbe19a8270bef5e1b12799fa38b20604b8103486f592da7daa77d7b0",
    "depends": "aws-tools-powershell-common",
    "psmodule": {
        "name": "AWS.Tools.ApiGatewayManagementApi"
    },
    "checkver": {
        "url": "https://www.powershellgallery.com/packages/AWS.Tools.ApiGatewayManagementApi",
        "regex": "Downloads? of ([\\d.]+)"
    },
    "autoupdate": {
        "url": "https://psg-prod-eastus.azureedge.net/packages/aws.tools.apigatewaymanagementapi.$version.nupkg"
    }
}
