{
    "version": "4.1.448",
    "description": "The LexRuntimeV2 module of AWS Tools for PowerShell lets developers and administrators manage Amazon Lex Runtime V2 from the PowerShell scripting environment",
    "homepage": "https://github.com/aws/aws-tools-for-powershell",
    "license": "Apache-2.0",
    "url": "https://psg-prod-eastus.azureedge.net/packages/aws.tools.lexruntimev2.4.1.448.nupkg",
    "hash": "e5bfe0c2f3109d4420cbaeda9eec29327cf2d8f2457ad6641204383a31c0bee8",
    "depends": "aws-tools-powershell-common",
    "psmodule": {
        "name": "AWS.Tools.LexRuntimeV2"
    },
    "checkver": {
        "url": "https://www.powershellgallery.com/packages/AWS.Tools.LexRuntimeV2",
        "regex": "Downloads? of ([\\d.]+)"
    },
    "autoupdate": {
        "url": "https://psg-prod-eastus.azureedge.net/packages/aws.tools.lexruntimev2.$version.nupkg"
    }
}
