{
    "version": "4.1.595",
    "description": "The ManagedBlockchain module of AWS Tools for PowerShell lets developers and administrators manage Amazon Managed Blockchain from the PowerShell scripting environment",
    "homepage": "https://github.com/aws/aws-tools-for-powershell",
    "license": "Apache-2.0",
    "url": "https://psg-prod-eastus.azureedge.net/packages/aws.tools.managedblockchain.4.1.595.nupkg",
    "hash": "7eee1e7c3c9c4b8d60a80d959b3b19de7c3f92918d9c35ae739ca94b54c65f93",
    "depends": "aws-tools-powershell-common",
    "psmodule": {
        "name": "AWS.Tools.ManagedBlockchain"
    },
    "checkver": {
        "url": "https://www.powershellgallery.com/packages/AWS.Tools.ManagedBlockchain",
        "regex": "Downloads? of ([\\d.]+)"
    },
    "autoupdate": {
        "url": "https://psg-prod-eastus.azureedge.net/packages/aws.tools.managedblockchain.$version.nupkg"
    }
}
