{
    "version": "4.1.477",
    "description": "The Route53RecoveryCluster module of AWS Tools for PowerShell lets developers and administrators manage Route53 Recovery Cluster from the PowerShell scripting environment",
    "homepage": "https://github.com/aws/aws-tools-for-powershell",
    "license": "Apache-2.0",
    "url": "https://psg-prod-eastus.azureedge.net/packages/aws.tools.route53recoverycluster.4.1.477.nupkg",
    "hash": "c79ee4d4cae32a51f85cd9723ddce0d5cdf32a6dce1c2ce2452e45c85e292807",
    "depends": "aws-tools-powershell-common",
    "psmodule": {
        "name": "AWS.Tools.Route53RecoveryCluster"
    },
    "checkver": {
        "url": "https://www.powershellgallery.com/packages/AWS.Tools.Route53RecoveryCluster",
        "regex": "Downloads? of ([\\d.]+)"
    },
    "autoupdate": {
        "url": "https://psg-prod-eastus.azureedge.net/packages/aws.tools.route53recoverycluster.$version.nupkg"
    }
}
