{
    "version": "4.1.403",
    "description": "The FraudDetector module of AWS Tools for PowerShell lets developers and administrators manage Amazon Fraud Detector from the PowerShell scripting environment",
    "homepage": "https://github.com/aws/aws-tools-for-powershell",
    "license": "Apache-2.0",
    "url": "https://psg-prod-eastus.azureedge.net/packages/aws.tools.frauddetector.4.1.403.nupkg",
    "hash": "e62ef2ef87e61185f403fc52f9b555b5dc0f8b419ab9d8d2a900ceed073f5a13",
    "depends": "aws-tools-powershell-common",
    "psmodule": {
        "name": "AWS.Tools.FraudDetector"
    },
    "checkver": {
        "url": "https://www.powershellgallery.com/packages/AWS.Tools.FraudDetector",
        "regex": "Downloads? of ([\\d.]+)"
    },
    "autoupdate": {
        "url": "https://psg-prod-eastus.azureedge.net/packages/aws.tools.frauddetector.$version.nupkg"
    }
}
