{
    "version": "4.1.416",
    "description": "The DevOpsGuru module of AWS Tools for PowerShell lets developers and administrators manage Amazon DevOps Guru from the PowerShell scripting environment",
    "homepage": "https://github.com/aws/aws-tools-for-powershell",
    "license": "Apache-2.0",
    "url": "https://psg-prod-eastus.azureedge.net/packages/aws.tools.devopsguru.4.1.416.nupkg",
    "hash": "0942ee1d88d3f3c1cd67136a5bc417b97d04f727cdfe1313fceed05322502d8a",
    "depends": "aws-tools-powershell-common",
    "psmodule": {
        "name": "AWS.Tools.DevOpsGuru"
    },
    "checkver": {
        "url": "https://www.powershellgallery.com/packages/AWS.Tools.DevOpsGuru",
        "regex": "Downloads? of ([\\d.]+)"
    },
    "autoupdate": {
        "url": "https://psg-prod-eastus.azureedge.net/packages/aws.tools.devopsguru.$version.nupkg"
    }
}
