{
    "version": "4.1.453",
    "description": "The LicenseManager module of AWS Tools for PowerShell lets developers and administrators manage AWS License Manager from the PowerShell scripting environment",
    "homepage": "https://github.com/aws/aws-tools-for-powershell",
    "license": "Apache-2.0",
    "url": "https://psg-prod-eastus.azureedge.net/packages/aws.tools.licensemanager.4.1.453.nupkg",
    "hash": "a7b9eea4a06d5ae328d1246686c9df571d860f832481add36c9b0a7b39be108c",
    "depends": "aws-tools-powershell-common",
    "psmodule": {
        "name": "AWS.Tools.LicenseManager"
    },
    "checkver": {
        "url": "https://www.powershellgallery.com/packages/AWS.Tools.LicenseManager",
        "regex": "Downloads? of ([\\d.]+)"
    },
    "autoupdate": {
        "url": "https://psg-prod-eastus.azureedge.net/packages/aws.tools.licensemanager.$version.nupkg"
    }
}
