{
    "version": "4.1.620",
    "description": "The CodeStar module of AWS Tools for PowerShell lets developers and administrators manage AWS CodeStar from the PowerShell scripting environment",
    "homepage": "https://github.com/aws/aws-tools-for-powershell",
    "license": "Apache-2.0",
    "url": "https://psg-prod-eastus.azureedge.net/packages/aws.tools.codestar.4.1.620.nupkg",
    "hash": "ba6f97f36ccf532a69f6dfed80bc29c1f1b4dd12f0f98e5560c4c27ab7cede1a",
    "depends": "aws-tools-powershell-common",
    "psmodule": {
        "name": "AWS.Tools.CodeStar"
    },
    "checkver": {
        "url": "https://www.powershellgallery.com/packages/AWS.Tools.CodeStar",
        "regex": "Downloads? of ([\\d.]+)"
    },
    "autoupdate": {
        "url": "https://psg-prod-eastus.azureedge.net/packages/aws.tools.codestar.$version.nupkg"
    }
}
