{
    "version": "4.1.610",
    "description": "The MigrationHubConfig module of AWS Tools for PowerShell lets developers and administrators manage AWS Migration Hub Config from the PowerShell scripting environment",
    "homepage": "https://github.com/aws/aws-tools-for-powershell",
    "license": "Apache-2.0",
    "url": "https://psg-prod-eastus.azureedge.net/packages/aws.tools.migrationhubconfig.4.1.610.nupkg",
    "hash": "603127f9e9ca573e39dd20ae7497278f090ceb9344bd0da0aa65c90f7209305c",
    "depends": "aws-tools-powershell-common",
    "psmodule": {
        "name": "AWS.Tools.MigrationHubConfig"
    },
    "checkver": {
        "url": "https://www.powershellgallery.com/packages/AWS.Tools.MigrationHubConfig",
        "regex": "Downloads? of ([\\d.]+)"
    },
    "autoupdate": {
        "url": "https://psg-prod-eastus.azureedge.net/packages/aws.tools.migrationhubconfig.$version.nupkg"
    }
}
