{
    "version": "4.1.370",
    "description": "The DatabaseMigrationService module of AWS Tools for PowerShell lets developers and administrators manage AWS Database Migration Service from the PowerShell scripting environment",
    "homepage": "https://github.com/aws/aws-tools-for-powershell",
    "license": "Apache-2.0",
    "url": "https://psg-prod-eastus.azureedge.net/packages/aws.tools.databasemigrationservice.4.1.370.nupkg",
    "hash": "7328282e3c245f7b1515f89b118d3125fbd6df5119b7c5625a29ce974ee0a0bf",
    "depends": "aws-tools-powershell-common",
    "psmodule": {
        "name": "AWS.Tools.DatabaseMigrationService"
    },
    "checkver": {
        "url": "https://www.powershellgallery.com/packages/AWS.Tools.DatabaseMigrationService",
        "regex": "Downloads? of ([\\d.]+)"
    },
    "autoupdate": {
        "url": "https://psg-prod-eastus.azureedge.net/packages/aws.tools.databasemigrationservice.$version.nupkg"
    }
}
