{
    "version": "4.1.634",
    "description": "The KinesisVideo module of AWS Tools for PowerShell lets developers and administrators manage Amazon Kinesis Video Streams from the PowerShell scripting environment",
    "homepage": "https://github.com/aws/aws-tools-for-powershell",
    "license": "Apache-2.0",
    "url": "https://psg-prod-eastus.azureedge.net/packages/aws.tools.kinesisvideo.4.1.634.nupkg",
    "hash": "6004ebc458c245cff524459459404b1dbc1857c07c08e79204dc33dd3502e89a",
    "depends": "aws-tools-powershell-common",
    "psmodule": {
        "name": "AWS.Tools.KinesisVideo"
    },
    "checkver": {
        "url": "https://www.powershellgallery.com/packages/AWS.Tools.KinesisVideo",
        "regex": "Downloads? of ([\\d.]+)"
    },
    "autoupdate": {
        "url": "https://psg-prod-eastus.azureedge.net/packages/aws.tools.kinesisvideo.$version.nupkg"
    }
}
