{
    "version": "4.1.414",
    "description": "The IoTJobsDataPlane module of AWS Tools for PowerShell lets developers and administrators manage AWS IoT Jobs Data Plane from the PowerShell scripting environment",
    "homepage": "https://github.com/aws/aws-tools-for-powershell",
    "license": "Apache-2.0",
    "url": "https://psg-prod-eastus.azureedge.net/packages/aws.tools.iotjobsdataplane.4.1.414.nupkg",
    "hash": "8139644534414f7b9ccff3ee5556ff27b66c9b7b2e691d65058da36dce6b1db6",
    "depends": "aws-tools-powershell-common",
    "psmodule": {
        "name": "AWS.Tools.IoTJobsDataPlane"
    },
    "checkver": {
        "url": "https://www.powershellgallery.com/packages/AWS.Tools.IoTJobsDataPlane",
        "regex": "Downloads? of ([\\d.]+)"
    },
    "autoupdate": {
        "url": "https://psg-prod-eastus.azureedge.net/packages/aws.tools.iotjobsdataplane.$version.nupkg"
    }
}
