{
    "version": "4.1.353",
    "description": "The DeviceFarm module of AWS Tools for PowerShell lets developers and administrators manage AWS Device Farm from the PowerShell scripting environment",
    "homepage": "https://github.com/aws/aws-tools-for-powershell",
    "license": "Apache-2.0",
    "url": "https://psg-prod-eastus.azureedge.net/packages/aws.tools.devicefarm.4.1.353.nupkg",
    "hash": "c92587bd6278689e7e24db727cd1260364f12fc60266eaf655ff9453b6e1671b",
    "depends": "aws-tools-powershell-common",
    "psmodule": {
        "name": "AWS.Tools.DeviceFarm"
    },
    "checkver": {
        "url": "https://www.powershellgallery.com/packages/AWS.Tools.DeviceFarm",
        "regex": "Downloads? of ([\\d.]+)"
    },
    "autoupdate": {
        "url": "https://psg-prod-eastus.azureedge.net/packages/aws.tools.devicefarm.$version.nupkg"
    }
}
