{
    "version": "4.1.488",
    "description": "The ConnectContactLens module of AWS Tools for PowerShell lets developers and administrators manage Amazon Connect Contact Lens from the PowerShell scripting environment",
    "homepage": "https://github.com/aws/aws-tools-for-powershell",
    "license": "Apache-2.0",
    "url": "https://psg-prod-eastus.azureedge.net/packages/aws.tools.connectcontactlens.4.1.488.nupkg",
    "hash": "322b048025baa84043dfa46d1f69bc9659a0ffd3c05b37f06df0edb8a13939eb",
    "depends": "aws-tools-powershell-common",
    "psmodule": {
        "name": "AWS.Tools.ConnectContactLens"
    },
    "checkver": {
        "url": "https://www.powershellgallery.com/packages/AWS.Tools.ConnectContactLens",
        "regex": "Downloads? of ([\\d.]+)"
    },
    "autoupdate": {
        "url": "https://psg-prod-eastus.azureedge.net/packages/aws.tools.connectcontactlens.$version.nupkg"
    }
}
