{
    "version": "4.1.119",
    "description": "The DataSync module of AWS Tools for PowerShell lets developers and administrators manage AWS DataSync from the PowerShell scripting environment",
    "homepage": "https://github.com/aws/aws-tools-for-powershell",
    "license": "Apache-2.0",
    "url": "https://psg-prod-eastus.azureedge.net/packages/aws.tools.datasync.4.1.119.nupkg",
    "hash": "d1988ffc860988dfed818b2af3f47d47f6446e0dd0c737452c4660e82a85135a",
    "depends": "aws-tools-powershell-common",
    "psmodule": {
        "name": "AWS.Tools.DataSync"
    },
    "checkver": {
        "url": "https://www.powershellgallery.com/packages/AWS.Tools.DataSync",
        "regex": "Downloads? of ([\\d.]+)"
    },
    "autoupdate": {
        "url": "https://psg-prod-eastus.azureedge.net/packages/aws.tools.datasync.$version.nupkg"
    }
}
