{
    "version": "4.1.661",
    "description": "The Keyspaces module of AWS Tools for PowerShell lets developers and administrators manage Amazon Keyspaces from the PowerShell scripting environment",
    "homepage": "https://github.com/aws/aws-tools-for-powershell",
    "license": "Apache-2.0",
    "url": "https://psg-prod-eastus.azureedge.net/packages/aws.tools.keyspaces.4.1.661.nupkg",
    "hash": "0f0e5a56c27305a3c7b9dc788589095cdd375d011b61b4e2343522e08bb8edf8",
    "depends": "aws-tools-powershell-common",
    "psmodule": {
        "name": "AWS.Tools.Keyspaces"
    },
    "checkver": {
        "url": "https://www.powershellgallery.com/packages/AWS.Tools.Keyspaces",
        "regex": "Downloads? of ([\\d.]+)"
    },
    "autoupdate": {
        "url": "https://psg-prod-eastus.azureedge.net/packages/aws.tools.keyspaces.$version.nupkg"
    }
}
