{
    "version": "4.1.378",
    "description": "The CognitoIdentityProvider module of AWS Tools for PowerShell lets developers and administrators manage Amazon Cognito Identity Provider from the PowerShell scripting environment",
    "homepage": "https://github.com/aws/aws-tools-for-powershell",
    "license": "Apache-2.0",
    "url": "https://psg-prod-eastus.azureedge.net/packages/aws.tools.cognitoidentityprovider.4.1.378.nupkg",
    "hash": "d3c915b4467487599ab2d4512ef07c6b3baf8cc401b0cb7580d00bb5e8542ba8",
    "depends": "aws-tools-powershell-common",
    "psmodule": {
        "name": "AWS.Tools.CognitoIdentityProvider"
    },
    "checkver": {
        "url": "https://www.powershellgallery.com/packages/AWS.Tools.CognitoIdentityProvider",
        "regex": "Downloads? of ([\\d.]+)"
    },
    "autoupdate": {
        "url": "https://psg-prod-eastus.azureedge.net/packages/aws.tools.cognitoidentityprovider.$version.nupkg"
    }
}
